easy_testing/__init__.py
easy_testing/builders.py
easy_testing/dataframes.py
scalde_easy_testing-0.0.1.dist-info/METADATA
scalde_easy_testing-0.0.1.dist-info/WHEEL
scalde_easy_testing-0.0.1.dist-info/top_level.txt
scalde_easy_testing-0.0.1.dist-info/RECORD
